[
  {
    "id": 1,
    "name": "ChaosGrom",
    "image": "/images/characters/ChoasGrom.png",
    "clicked": false
  },
  {
    "id": 2,
    "name": "Demoness",
    "image": "/images/characters/Demoness.png",
    "clicked": false
  },
  {
    "id": 3,
    "name": "DeathKnightArthas",
    "image": "/images/characters/DKArthas.png",
    "clicked": false
  },
  {
    "id": 4,
    "name": "Dragon",
    "image": "/images/characters/Dragon.png",
    "clicked": false
  },
  {
    "id": 5,
    "name": "Dryad",
    "image": "/images/characters/Dryad.png",
    "clicked": false
  },
  {
    "id": 6,
    "name": "ElfVillager",
    "image": "/images/characters/ElfVillager.png",
    "clicked": false
  },
  {
    "id": 7,
    "name": "FlyingMachine",
    "image": "/images/characters/FlyingMachine.png",
    "clicked": false
  },
  {
    "id": 8,
    "name": "Gul'dan",
    "image": "/images/characters/Guldan.png",
    "clicked": false
  },
  {
    "id": 9,
    "name": "Headhunter",
    "image": "/images/characters/Headhunter.png",
    "clicked": false
  },
  {
    "id": 10,
    "name": "Kael'thas",
    "image": "/images/characters/Kael'thas.png",
    "clicked": false
  },
  {
    "id": 11,
    "name": "KelThuzad",
    "image": "/images/characters/KelThuzad.png",
    "clicked": false
  },
  {
    "id": 12,
    "name": "Maiev",
    "image": "/images/characters/Maiev.png",
    "clicked": false
  },
  {
    "id": 13,
    "name": "Malfurion",
    "image": "/images/characters/Malfurion.png",
    "clicked": false
  },
  {
    "id": 14,
    "name": "Medivh",
    "image": "/images/characters/Medivh.png",
    "clicked": false
  },
  {
    "id": 15,
    "name": "MortarTeam",
    "image": "/images/characters/MortarTeam.png",
    "clicked": false
  },
  {
    "id": 16,
    "name": "Muradin",
    "image": "/images/characters/Muradin.png",
    "clicked": false
  },
  {
    "id": 17,
    "name": "Necromancer",
    "image": "/images/characters/Necromancer.png",
    "clicked": false
  },
  {
    "id": 18,
    "name": "Rexxar",
    "image": "/images/characters/Rexxar.png",
    "clicked": false
  },
  {
    "id": 19,
    "name": "SeaWitch",
    "image": "/images/characters/SeaWitch.png",
    "clicked": false
  },
  {
    "id": 20,
    "name": "Shaman",
    "image": "/images/characters/Shaman.png",
    "clicked": false
  },
  {
    "id": 21,
    "name": "ChenStormstout",
    "image": "/images/characters/Stormstout.png",
    "clicked": false
  },
  {
    "id": 22,
    "name": "Sylvanas",
    "image": "/images/characters/Sylvanas.png",
    "clicked": false
  },
  {
    "id": 23,
    "name": "Thrall",
    "image": "/images/characters/Thrall.png",
    "clicked": false
  },
  {
    "id": 24,
    "name": "IllidanMetamorphisis",
    "image": "/images/characters/Illidan.png",
    "clicked": false
  }
]